{
	"title": "ServiceMethod管理",
	"columns": [{
		"name" : "id",
		"dataIndex" : "code",
		"type" : "TextField",
		"canList" : false,
		"canSearch" : false,
		"canAdd" : false,
		"canBatchAdd" : false,
		"canUpdate" : false,
		"canReport" : true,
		"canOrder" : true,
		"display" : null,
		"orderNum" : 2
	},
	{
		"name" : "父类",
		"dataIndex" : "parent",
		"type" : "ComboBox",
		"canList" : true,
		"canSearch" : true,
		"canAdd" : true,
		"canBatchAdd" : true,
		"canUpdate" : true,
		"canReport" : true,
		"canOrder" : true,
		"comboUrl" : "/dev/service/method/myList.json",
		"display" : null,
		"orderNum" : 3
	},
	{
		"name" : "名称",
		"dataIndex" : "name",
		"type" : "TextField",
		"canList" : true,
		"canSearch" : true,
		"canAdd" : true,
		"canBatchAdd" : true,
		"canUpdate" : true,
		"canReport" : true,
		"canOrder" : true,
		"display" : null,
		"orderNum" : 4
	},
	
	{
		"name" : "返回",
		"dataIndex" : "ret.name",
		"type" : "TextField",
		"canList" : true,
		"canSearch" : true,
		"canAdd" : true,
		"canBatchAdd" : true,
		"canUpdate" : true,
		"canReport" : true,
		"canOrder" : true,
		"display" : null,
		"orderNum" : 5
	},
	{
		"name" : "参数",
		"dataIndex" : "paramStr",
		"type" : "TextField",
		"canList" : true,
		"canSearch" : true,
		"canAdd" : true,
		"canBatchAdd" : true,
		"canUpdate" : true,
		"canReport" : true,
		"canOrder" : true,
		"display" : null,
		"orderNum" : 6
	},
	{
		"name" : "流程",
		"dataIndex" : "sqlStr",
		"type" : "TextField",
		"canList" : true,
		"canSearch" : true,
		"canAdd" : true,
		"canBatchAdd" : true,
		"canUpdate" : true,
		"canReport" : true,
		"canOrder" : true,
		"display" : null,
		"orderNum" : 7
	},
	{
		"name" : "备注",
		"dataIndex" : "comment",
		"type" : "TextField",
		"canList" : true,
		"canSearch" : true,
		"canAdd" : true,
		"canBatchAdd" : true,
		"canUpdate" : true,
		"canReport" : true,
		"canOrder" : true,
		"display" : null,
		"orderNum" : 8
	},
	{
		"name" : "Service名称",
		"dataIndex" : "service.name",
		"type" : "Hidden",
		"canList" : false,
		"canSearch" : false,
		"canAdd" : true,
		"canBatchAdd" : false,
		"canUpdate" : true,
		"canReport" : false,
		"canOrder" : false,
		"display" : "${param.serviceName}",
		"orderNum" : 4
	},
	{
		"name" : "模块code",
		"dataIndex" : "service.module.code",
		"type" : "Hidden",
		"canList" : false,
		"canSearch" : false,
		"canAdd" : true,
		"canBatchAdd" : false,
		"canUpdate" : true,
		"canReport" : false,
		"canOrder" : false,
		"display" : "${param.moduleCode}",
		"orderNum" : 4
	}],
	"menus" : [{
		"name" : "返回",
		"canSelect" : false,
		"isSingleSelect" : false,
		"checkColumn" : '',
		"actionAddress" : '../../service/?moduleCode=${param.moduleCode}',
		"ajaxReturn" : false,
		"confirm": false,
		"title" : null,
		"fields" : null,
		"orderNum" : 1
	}],
	"isPrepared" : true,
	"canAdd" : true,
	"canBatchAdd" : false,
	"canDelete" : false,
	"canUpdate" : true,
	"canSearch" : false
}